<?xml version="1.0" encoding="utf-8"?>
<plugin id="gentoo">
  <public-mirror-database id="gentoo">
    <filename>plugin.py</filename>
    <classname>Db</classname>
  </public-mirror-database>
  <public-mirror-database id="gentoo-portage">
    <filename>plugin.py</filename>
    <classname>PortageDb</classname>
  </public-mirror-database>
  <mirror-site id="gentoo">
    <name>Gentoo Source Mirror</name>
    <data-directory>gentoo</data-directory>
    <updater>
      <filename>plugin.py</filename>
      <classname>Updater</classname>
      <scheduler>periodical</scheduler>
      <cron-expression>0 */4 * * *</cron-expression>
    </updater>
    <advertiser>
      <protocol>http</protocol>
      <protocol>ftp</protocol>
    </advertiser>
  </mirror-site>
  <mirror-site id="gentoo-portage">
    <name>Gentoo Portage</name>
    <data-directory>gentoo-portage</data-directory>
    <updater>
      <filename>plugin.py</filename>
      <classname>PortageUpdater</classname>
      <scheduler>periodical</scheduler>
      <cron-expression>0 */4 * * *</cron-expression>
    </updater>
    <advertiser>
      <protocol>rsync</protocol>
    </advertiser>
  </mirror-site>
</plugin>
